[
  {
    "approvalId": "APP-PO-5166",
    "requisitionId": "REQ-2026-00083",
    "vendorName": "ABC Infotech Private Limited",
    "department": "IT Services",
    "estimatedValue": 1187500,
    "currentStage": "Approved",
    "assignedTo": "",
    "status": "Approved",
    "remarks": "",
    "submittedBy": "Saurabh Anand",
    "submittedOn": "17/6/2026, 5:38:53 pm",
    "history": [
      {
        "action": "Submitted",
        "by": "Saurabh Anand",
        "dateTime": "17/6/2026, 5:38:53 pm"
      },
      {
        "action": "Department Head Approval Approved",
        "by": "Saurabh Anand",
        "dateTime": "17/6/2026, 5:39:09 pm",
        "remarks": ""
      },
      {
        "action": "Finance Approval Approved",
        "by": "Saurabh Anand",
        "dateTime": "17/6/2026, 5:39:16 pm",
        "remarks": ""
      },
      {
        "action": "Procurement Head Approval Approved",
        "by": "Saurabh Anand",
        "dateTime": "18/6/2026, 10:12:29 am",
        "remarks": ""
      }
    ]
  },
  {
    "approvalId": "APP-PO-5927",
    "requisitionId": "REQ-2026-00084",
    "vendorName": "New Age Software Solutions",
    "department": "IT Services",
    "estimatedValue": 1400000,
    "currentStage": "Department Head Approval",
    "assignedTo": "Priya Sharma",
    "status": "Pending",
    "remarks": "",
    "submittedBy": "Saurabh Anand",
    "submittedOn": "18/6/2026, 10:21:04 am",
    "history": [
      {
        "action": "Submitted",
        "by": "Saurabh Anand",
        "dateTime": "18/6/2026, 10:21:04 am"
      }
    ]
  },
  {
    "approvalId": "APP-PO-1183",
    "requisitionId": "REQ-2026-00085",
    "vendorName": "ABC Infotech Private Limited",
    "department": "IT Services",
    "estimatedValue": 1187500,
    "currentStage": "Department Head Approval",
    "assignedTo": "Priya Sharma",
    "status": "Pending",
    "remarks": "",
    "submittedBy": "Saurabh Anand",
    "submittedOn": "18/6/2026, 7:40:18 pm",
    "history": [
      {
        "action": "Submitted",
        "by": "Saurabh Anand",
        "dateTime": "18/6/2026, 7:40:18 pm"
      }
    ]
  },
  {
    "approvalId": "APP-PO-4031",
    "requisitionId": "REQ-2026-00086",
    "vendorName": "ABC Infotech Pvt Ltd, HDFC Bank Limited",
    "department": "IT Services",
    "estimatedValue": 1250000,
    "currentStage": "Department Head Approval",
    "assignedTo": "Priya Sharma",
    "status": "Pending",
    "remarks": "",
    "submittedBy": "Saurabh Anand",
    "submittedOn": "18/6/2026, 7:53:43 pm",
    "history": [
      {
        "action": "Submitted",
        "by": "Saurabh Anand",
        "dateTime": "18/6/2026, 7:53:43 pm"
      }
    ]
  },
  {
    "approvalId": "APP-PO-8806",
    "requisitionId": "REQ-2026-00087",
    "vendorName": "ABC Infotech Pvt Ltd, HDFC Bank Limited",
    "department": "IT Services",
    "estimatedValue": 1250000,
    "currentStage": "Department Head Approval",
    "assignedTo": "Priya Sharma",
    "status": "Pending",
    "remarks": "",
    "submittedBy": "Saurabh Anand",
    "submittedOn": "18/6/2026, 7:55:15 pm",
    "history": [
      {
        "action": "Submitted",
        "by": "Saurabh Anand",
        "dateTime": "18/6/2026, 7:55:15 pm"
      }
    ]
  },
  {
    "approvalId": "APP-PO-7790",
    "requisitionId": "REQ-2026-00088",
    "vendorName": "ABC Infotech Pvt Ltd, HDFC Bank Limited",
    "department": "IT Services",
    "estimatedValue": 1250000,
    "currentStage": "Department Head Approval",
    "assignedTo": "Priya Sharma",
    "status": "Pending",
    "remarks": "",
    "submittedBy": "Saurabh Anand",
    "submittedOn": "18/6/2026, 7:55:38 pm",
    "history": [
      {
        "action": "Submitted",
        "by": "Saurabh Anand",
        "dateTime": "18/6/2026, 7:55:38 pm"
      }
    ]
  },
  {
    "approvalId": "APP-PO-9204",
    "requisitionId": "REQ-2026-00089",
    "vendorName": "ABC Infotech Pvt Ltd, HDFC Bank Limited",
    "department": "IT Services",
    "estimatedValue": 1250000,
    "currentStage": "Department Head Approval",
    "assignedTo": "Priya Sharma",
    "status": "Pending",
    "remarks": "",
    "submittedBy": "Saurabh Anand",
    "submittedOn": "18/6/2026, 7:56:03 pm",
    "history": [
      {
        "action": "Submitted",
        "by": "Saurabh Anand",
        "dateTime": "18/6/2026, 7:56:03 pm"
      }
    ]
  },
  {
    "approvalId": "APP-PO-2958",
    "requisitionId": "REQ-2026-00090",
    "vendorName": "ABC Infotech Pvt Ltd, HDFC Bank Limited",
    "department": "IT Services",
    "estimatedValue": 1250000,
    "currentStage": "Department Head Approval",
    "assignedTo": "Priya Sharma",
    "status": "Pending",
    "remarks": "",
    "submittedBy": "Saurabh Anand",
    "submittedOn": "18/6/2026, 8:11:57 pm",
    "history": [
      {
        "action": "Submitted",
        "by": "Saurabh Anand",
        "dateTime": "18/6/2026, 8:11:57 pm"
      }
    ]
  },
  {
    "approvalId": "APP-PO-9109",
    "requisitionId": "REQ-2026-00091",
    "vendorName": "ABC Infotech Pvt Ltd, HDFC Bank Limited",
    "department": "Facilities",
    "estimatedValue": 1250000,
    "currentStage": "Department Head Approval",
    "assignedTo": "Priya Sharma",
    "status": "Pending",
    "remarks": "",
    "submittedBy": "Saurabh Anand",
    "submittedOn": "18/6/2026, 8:13:29 pm",
    "history": [
      {
        "action": "Submitted",
        "by": "Saurabh Anand",
        "dateTime": "18/6/2026, 8:13:29 pm"
      }
    ]
  }
]