{
  "totalActiveContracts": 2,
  "expiringSoon": 0,
  "pendingLegalReviews": 1,
  "slaBreaches": 0,
  "lifecycleDistribution": [
    {
      "name": "Active",
      "value": 2,
      "color": "#16A34A"
    },
    {
      "name": "Draft",
      "value": 0,
      "color": "#94A3B8"
    },
    {
      "name": "Under Review",
      "value": 1,
      "color": "#F59E0B"
    },
    {
      "name": "Expired",
      "value": 0,
      "color": "#EF4444"
    }
  ],
  "contractValueByCategory": [
    {
      "category": "IT Services",
      "spend": 2.4
    },
    {
      "category": "Facilities",
      "spend": 0
    },
    {
      "category": "Legal",
      "spend": 0
    },
    {
      "category": "Cloud",
      "spend": 0
    },
    {
      "category": "Consulting",
      "spend": 0
    }
  ],
  "portfolioRisk": "Medium",
  "legalExposure": 52,
  "complianceRisk": 22,
  "financialRisk": 67,
  "vendorRiskAnalysis": [
    {
      "name": "High Risk",
      "value": 1
    },
    {
      "name": "Medium Risk",
      "value": 1
    },
    {
      "name": "Low Risk",
      "value": 0
    }
  ]
}